openVulnQuery/__init__.py
openVulnQuery/main.py
openVulnQuery/_library/__init__.py
openVulnQuery/_library/_compatibility.py
openVulnQuery/_library/advisory.py
openVulnQuery/_library/authorization.py
openVulnQuery/_library/cli_api.py
openVulnQuery/_library/config.py
openVulnQuery/_library/constants.py
openVulnQuery/_library/main.py
openVulnQuery/_library/query_client.py
openVulnQuery/_library/rest_api.py
openVulnQuery/_library/utils.py
OpenVulnQuery-1.31.dist-info/LICENSE
OpenVulnQuery-1.31.dist-info/METADATA
OpenVulnQuery-1.31.dist-info/WHEEL
OpenVulnQuery-1.31.dist-info/entry_points.txt
OpenVulnQuery-1.31.dist-info/top_level.txt
OpenVulnQuery-1.31.dist-info/RECORD
