Metadata-Version: 2.1
Name: OpenVulnQuery
Version: 1.31
Summary: A python-based module(s) to query the Cisco PSIRT openVuln API.
Home-page: https://github.com/CiscoPSIRT/openVulnAPI/tree/master/openVulnQuery
Author:  Omar Santos
Author-email: os@cisco.com
License: The MIT License (MIT)
Platform: UNKNOWN
